manim_sequence_diagram/__init__.py
manim_sequence_diagram/constants.py
manim_sequence_diagram/seq_action.py
manim_sequence_diagram/seq_actor.py
manim_sequence_diagram/seq_object.py
manim_sequence_diagram-0.1.0.dist-info/WHEEL
manim_sequence_diagram-0.1.0.dist-info/entry_points.txt
manim_sequence_diagram-0.1.0.dist-info/LICENSE.txt
manim_sequence_diagram-0.1.0.dist-info/METADATA
manim_sequence_diagram-0.1.0.dist-info/RECORD
