Metadata-Version: 2.1
Name: manim-sequence-diagram
Version: 0.1.0
Summary: Manim extension to generate UML sequence diagrams
Home-page: https://github.com/foxnewsnetwork/manim-sequence-diagram
Author: Thomas Chen
Author-email: tom.chen@sony.com
Requires-Python: >=3.8,<4.0
Classifier: Development Status :: 3 - Alpha
Classifier: License :: OSI Approved :: MIT License
Classifier: Natural Language :: English
Classifier: Programming Language :: Python :: 3
Classifier: Programming Language :: Python :: 3.8
Classifier: Programming Language :: Python :: 3.9
Classifier: Programming Language :: Python :: 3.10
Classifier: Programming Language :: Python :: 3.11
Classifier: Programming Language :: Python :: 3.6
Classifier: Programming Language :: Python :: 3.7
Classifier: Programming Language :: Python :: 3.8
Classifier: Programming Language :: Python :: 3.9
Classifier: Topic :: Multimedia :: Graphics
Classifier: Topic :: Multimedia :: Video
Classifier: Topic :: Scientific/Engineering
Requires-Dist: manim (>=0.3)
Project-URL: Documentation, https://github.com/foxnewsnetwork/manim-sequence-diagram
Project-URL: Repository, https://github.com/foxnewsnetwork/manim-sequence-diagram
